{"name":"Iniciar sesion en Para Bank","id":"crear-cuenta-en-para-bank;iniciar-sesion-en-para-bank","testSteps":[{"number":1,"description":"Given Deseo ir a la pagina de \"https://parabank.parasoft.com/parabank/\"","duration":10292,"startTime":"2021-06-30T08:40:27.231-05:00[America/Bogota]","screenshots":[{"screenshot":"21700d4721846595b591d45a5eb49bc55643ce4e5a36a39a59fb47d2188dda33.png","timeStamp":1625060437523}],"result":"SUCCESS","precondition":false,"level":0,"children":[{"number":2,"description":"Angel Vivas opens the https://parabank.parasoft.com/parabank/","duration":9603,"startTime":"2021-06-30T08:40:27.876-05:00[America/Bogota]","screenshots":[{"screenshot":"21700d4721846595b591d45a5eb49bc55643ce4e5a36a39a59fb47d2188dda33.png","timeStamp":1625060437479}],"result":"SUCCESS","precondition":false,"level":1}]},{"number":3,"description":"When Ingreso nombre de usuario \"john\" y password \"demo\"","duration":31846,"startTime":"2021-06-30T08:40:37.525-05:00[America/Bogota]","screenshots":[{"screenshot":"21700d4721846595b591d45a5eb49bc55643ce4e5a36a39a59fb47d2188dda33.png","timeStamp":1625060437936}],"exception":{"errorType":"org.openqa.selenium.NoSuchElementException","message":"Cannot locate option with value: 12789\nFor documentation on this error, please visit: https://www.seleniumhq.org/exceptions/no_such_element.html\nBuild info: version: \u00273.141.59\u0027, revision: \u0027e82be7d358\u0027, time: \u00272018-11-14T08:17:03\u0027\nSystem info: host: \u0027SSMED5CG1081FB1\u0027, ip: \u0027192.168.0.18\u0027, os.name: \u0027Windows 10\u0027, os.arch: \u0027amd64\u0027, os.version: \u002710.0\u0027, java.version: \u00271.8.0_291\u0027\nDriver info: driver.version: unknown","stackTrace":[{"declaringClass":"com.sophos.semillero.tasks.CreateAccount","methodName":"performAs","fileName":"CreateAccount.java","lineNumber":20},{"declaringClass":"com.sophos.semillero.stepdefinitions.LoginStepDefinitions","methodName":"ingresoNombreDeUsuarioYPassword","fileName":"LoginStepDefinitions.java","lineNumber":41},{"declaringClass":"io.cucumber.java.Invoker","methodName":"invoke","fileName":"Invoker.java","lineNumber":27},{"declaringClass":"io.cucumber.java.JavaStepDefinition","methodName":"execute","fileName":"JavaStepDefinition.java","lineNumber":27},{"declaringClass":"io.cucumber.core.runner.PickleStepDefinitionMatch","methodName":"runStep","fileName":"PickleStepDefinitionMatch.java","lineNumber":63},{"declaringClass":"io.cucumber.core.runner.TestStep","methodName":"executeStep","fileName":"TestStep.java","lineNumber":64},{"declaringClass":"io.cucumber.core.runner.TestStep","methodName":"run","fileName":"TestStep.java","lineNumber":49},{"declaringClass":"io.cucumber.core.runner.PickleStepTestStep","methodName":"run","fileName":"PickleStepTestStep.java","lineNumber":46},{"declaringClass":"io.cucumber.core.runner.TestCase","methodName":"run","fileName":"TestCase.java","lineNumber":51},{"declaringClass":"io.cucumber.core.runner.Runner","methodName":"runPickle","fileName":"Runner.java","lineNumber":67},{"declaringClass":"io.cucumber.junit.FeatureRunner","methodName":"runChild","fileName":"FeatureRunner.java","lineNumber":83},{"declaringClass":"io.cucumber.junit.FeatureRunner","methodName":"runChild","fileName":"FeatureRunner.java","lineNumber":24},{"declaringClass":"io.cucumber.junit.CucumberSerenityRunner","methodName":"runChild","fileName":"CucumberSerenityRunner.java","lineNumber":227},{"declaringClass":"io.cucumber.junit.CucumberSerenityRunner","methodName":"runChild","fileName":"CucumberSerenityRunner.java","lineNumber":54},{"declaringClass":"org.eclipse.jdt.internal.junit4.runner.JUnit4TestReference","methodName":"run","fileName":"JUnit4TestReference.java","lineNumber":89},{"declaringClass":"org.eclipse.jdt.internal.junit.runner.TestExecution","methodName":"run","fileName":"TestExecution.java","lineNumber":40},{"declaringClass":"org.eclipse.jdt.internal.junit.runner.RemoteTestRunner","methodName":"runTests","fileName":"RemoteTestRunner.java","lineNumber":541},{"declaringClass":"org.eclipse.jdt.internal.junit.runner.RemoteTestRunner","methodName":"runTests","fileName":"RemoteTestRunner.java","lineNumber":768},{"declaringClass":"org.eclipse.jdt.internal.junit.runner.RemoteTestRunner","methodName":"run","fileName":"RemoteTestRunner.java","lineNumber":464},{"declaringClass":"org.eclipse.jdt.internal.junit.runner.RemoteTestRunner","methodName":"main","fileName":"RemoteTestRunner.java","lineNumber":210}]},"result":"ERROR","precondition":false,"level":0,"children":[{"number":4,"description":"Angel vivas login","duration":6211,"startTime":"2021-06-30T08:40:37.954-05:00[America/Bogota]","screenshots":[{"screenshot":"4a861f68c874a95f2cf0072c701ec7a4d96e53c479d779ddafe232c3a9984f18.png","timeStamp":1625060444165}],"result":"SUCCESS","precondition":false,"level":1,"children":[{"number":5,"description":"Angel Vivas enters \u0027john\u0027 into Campo nombre de usuario","duration":1786,"startTime":"2021-06-30T08:40:38.011-05:00[America/Bogota]","screenshots":[{"screenshot":"165fffa0a38793bcbc66e28fd3828c700c697167d432f4db45f848f7b10a1bcf.png","timeStamp":1625060438449},{"screenshot":"e5021746fec361de27ed777d082b67952dc7c4813c3cc3389620a56868213e43.png","timeStamp":1625060439797}],"result":"SUCCESS","precondition":false,"level":2},{"number":6,"description":"Angel Vivas enters \u0027demo\u0027 into Campo contraseña","duration":1600,"startTime":"2021-06-30T08:40:39.802-05:00[America/Bogota]","screenshots":[{"screenshot":"e5021746fec361de27ed777d082b67952dc7c4813c3cc3389620a56868213e43.png","timeStamp":1625060439810},{"screenshot":"1f01b3bbc051df75f023f266442ee3192bdd01757c1c01d78236aeabe1c78703.png","timeStamp":1625060441402}],"result":"SUCCESS","precondition":false,"level":2},{"number":7,"description":"Angel Vivas clicks on Boton login","duration":2757,"startTime":"2021-06-30T08:40:41.404-05:00[America/Bogota]","screenshots":[{"screenshot":"1f01b3bbc051df75f023f266442ee3192bdd01757c1c01d78236aeabe1c78703.png","timeStamp":1625060441409},{"screenshot":"4a861f68c874a95f2cf0072c701ec7a4d96e53c479d779ddafe232c3a9984f18.png","timeStamp":1625060444161}],"result":"SUCCESS","precondition":false,"level":2}]},{"number":8,"description":"Angel vivas create account","duration":25177,"startTime":"2021-06-30T08:40:44.189-05:00[America/Bogota]","screenshots":[{"screenshot":"4a861f68c874a95f2cf0072c701ec7a4d96e53c479d779ddafe232c3a9984f18.png","timeStamp":1625060444194}],"exception":{"errorType":"org.openqa.selenium.NoSuchElementException","message":"Cannot locate option with value: 12789\nFor documentation on this error, please visit: https://www.seleniumhq.org/exceptions/no_such_element.html\nBuild info: version: \u00273.141.59\u0027, revision: \u0027e82be7d358\u0027, time: \u00272018-11-14T08:17:03\u0027\nSystem info: host: \u0027SSMED5CG1081FB1\u0027, ip: \u0027192.168.0.18\u0027, os.name: \u0027Windows 10\u0027, os.arch: \u0027amd64\u0027, os.version: \u002710.0\u0027, java.version: \u00271.8.0_291\u0027\nDriver info: driver.version: unknown","stackTrace":[{"declaringClass":"com.sophos.semillero.tasks.CreateAccount","methodName":"performAs","fileName":"CreateAccount.java","lineNumber":20},{"declaringClass":"com.sophos.semillero.stepdefinitions.LoginStepDefinitions","methodName":"ingresoNombreDeUsuarioYPassword","fileName":"LoginStepDefinitions.java","lineNumber":41},{"declaringClass":"io.cucumber.java.Invoker","methodName":"invoke","fileName":"Invoker.java","lineNumber":27},{"declaringClass":"io.cucumber.java.JavaStepDefinition","methodName":"execute","fileName":"JavaStepDefinition.java","lineNumber":27},{"declaringClass":"io.cucumber.core.runner.PickleStepDefinitionMatch","methodName":"runStep","fileName":"PickleStepDefinitionMatch.java","lineNumber":63},{"declaringClass":"io.cucumber.core.runner.TestStep","methodName":"executeStep","fileName":"TestStep.java","lineNumber":64},{"declaringClass":"io.cucumber.core.runner.TestStep","methodName":"run","fileName":"TestStep.java","lineNumber":49},{"declaringClass":"io.cucumber.core.runner.PickleStepTestStep","methodName":"run","fileName":"PickleStepTestStep.java","lineNumber":46},{"declaringClass":"io.cucumber.core.runner.TestCase","methodName":"run","fileName":"TestCase.java","lineNumber":51},{"declaringClass":"io.cucumber.core.runner.Runner","methodName":"runPickle","fileName":"Runner.java","lineNumber":67},{"declaringClass":"io.cucumber.junit.FeatureRunner","methodName":"runChild","fileName":"FeatureRunner.java","lineNumber":83},{"declaringClass":"io.cucumber.junit.FeatureRunner","methodName":"runChild","fileName":"FeatureRunner.java","lineNumber":24},{"declaringClass":"io.cucumber.junit.CucumberSerenityRunner","methodName":"runChild","fileName":"CucumberSerenityRunner.java","lineNumber":227},{"declaringClass":"io.cucumber.junit.CucumberSerenityRunner","methodName":"runChild","fileName":"CucumberSerenityRunner.java","lineNumber":54},{"declaringClass":"org.eclipse.jdt.internal.junit4.runner.JUnit4TestReference","methodName":"run","fileName":"JUnit4TestReference.java","lineNumber":89},{"declaringClass":"org.eclipse.jdt.internal.junit.runner.TestExecution","methodName":"run","fileName":"TestExecution.java","lineNumber":40},{"declaringClass":"org.eclipse.jdt.internal.junit.runner.RemoteTestRunner","methodName":"runTests","fileName":"RemoteTestRunner.java","lineNumber":541},{"declaringClass":"org.eclipse.jdt.internal.junit.runner.RemoteTestRunner","methodName":"runTests","fileName":"RemoteTestRunner.java","lineNumber":768},{"declaringClass":"org.eclipse.jdt.internal.junit.runner.RemoteTestRunner","methodName":"run","fileName":"RemoteTestRunner.java","lineNumber":464},{"declaringClass":"org.eclipse.jdt.internal.junit.runner.RemoteTestRunner","methodName":"main","fileName":"RemoteTestRunner.java","lineNumber":210}]},"result":"ERROR","precondition":false,"level":1,"children":[{"number":9,"description":"Angel Vivas clicks on Botón crear nueva cuenta","duration":2344,"startTime":"2021-06-30T08:40:44.216-05:00[America/Bogota]","screenshots":[{"screenshot":"4a861f68c874a95f2cf0072c701ec7a4d96e53c479d779ddafe232c3a9984f18.png","timeStamp":1625060444577},{"screenshot":"36b460ffc37f8c7a5552a46cdea016fb7c2f5545729120f449d0f9f643bfe622.png","timeStamp":1625060446560}],"result":"SUCCESS","precondition":false,"level":2},{"number":10,"description":"Angel Vivas selects 1 in Select con tipos de cuenta","duration":1624,"startTime":"2021-06-30T08:40:46.564-05:00[America/Bogota]","screenshots":[{"screenshot":"36b460ffc37f8c7a5552a46cdea016fb7c2f5545729120f449d0f9f643bfe622.png","timeStamp":1625060446571},{"screenshot":"c658e78451b89ef70c1a01feeadce33ac71ab7c6f4c37523efcec01cf9918071.png","timeStamp":1625060448187}],"result":"SUCCESS","precondition":false,"level":2},{"number":11,"description":"Angel Vivas selects 12789 in Select con cuentas creadas","duration":21169,"startTime":"2021-06-30T08:40:48.191-05:00[America/Bogota]","screenshots":[{"screenshot":"c658e78451b89ef70c1a01feeadce33ac71ab7c6f4c37523efcec01cf9918071.png","timeStamp":1625060448200},{"screenshot":"c658e78451b89ef70c1a01feeadce33ac71ab7c6f4c37523efcec01cf9918071.png","htmlSource":"pagesource7825450454407212519.html.txt","timeStamp":1625060469350}],"exception":{"errorType":"org.openqa.selenium.NoSuchElementException","message":"Cannot locate option with value: 12789\nFor documentation on this error, please visit: https://www.seleniumhq.org/exceptions/no_such_element.html\nBuild info: version: \u00273.141.59\u0027, revision: \u0027e82be7d358\u0027, time: \u00272018-11-14T08:17:03\u0027\nSystem info: host: \u0027SSMED5CG1081FB1\u0027, ip: \u0027192.168.0.18\u0027, os.name: \u0027Windows 10\u0027, os.arch: \u0027amd64\u0027, os.version: \u002710.0\u0027, java.version: \u00271.8.0_291\u0027\nDriver info: driver.version: unknown","stackTrace":[{"declaringClass":"com.sophos.semillero.tasks.CreateAccount","methodName":"performAs","fileName":"CreateAccount.java","lineNumber":20},{"declaringClass":"com.sophos.semillero.stepdefinitions.LoginStepDefinitions","methodName":"ingresoNombreDeUsuarioYPassword","fileName":"LoginStepDefinitions.java","lineNumber":41},{"declaringClass":"io.cucumber.java.Invoker","methodName":"invoke","fileName":"Invoker.java","lineNumber":27},{"declaringClass":"io.cucumber.java.JavaStepDefinition","methodName":"execute","fileName":"JavaStepDefinition.java","lineNumber":27},{"declaringClass":"io.cucumber.core.runner.PickleStepDefinitionMatch","methodName":"runStep","fileName":"PickleStepDefinitionMatch.java","lineNumber":63},{"declaringClass":"io.cucumber.core.runner.TestStep","methodName":"executeStep","fileName":"TestStep.java","lineNumber":64},{"declaringClass":"io.cucumber.core.runner.TestStep","methodName":"run","fileName":"TestStep.java","lineNumber":49},{"declaringClass":"io.cucumber.core.runner.PickleStepTestStep","methodName":"run","fileName":"PickleStepTestStep.java","lineNumber":46},{"declaringClass":"io.cucumber.core.runner.TestCase","methodName":"run","fileName":"TestCase.java","lineNumber":51},{"declaringClass":"io.cucumber.core.runner.Runner","methodName":"runPickle","fileName":"Runner.java","lineNumber":67},{"declaringClass":"io.cucumber.junit.FeatureRunner","methodName":"runChild","fileName":"FeatureRunner.java","lineNumber":83},{"declaringClass":"io.cucumber.junit.FeatureRunner","methodName":"runChild","fileName":"FeatureRunner.java","lineNumber":24},{"declaringClass":"io.cucumber.junit.CucumberSerenityRunner","methodName":"runChild","fileName":"CucumberSerenityRunner.java","lineNumber":227},{"declaringClass":"io.cucumber.junit.CucumberSerenityRunner","methodName":"runChild","fileName":"CucumberSerenityRunner.java","lineNumber":54},{"declaringClass":"org.eclipse.jdt.internal.junit4.runner.JUnit4TestReference","methodName":"run","fileName":"JUnit4TestReference.java","lineNumber":89},{"declaringClass":"org.eclipse.jdt.internal.junit.runner.TestExecution","methodName":"run","fileName":"TestExecution.java","lineNumber":40},{"declaringClass":"org.eclipse.jdt.internal.junit.runner.RemoteTestRunner","methodName":"runTests","fileName":"RemoteTestRunner.java","lineNumber":541},{"declaringClass":"org.eclipse.jdt.internal.junit.runner.RemoteTestRunner","methodName":"runTests","fileName":"RemoteTestRunner.java","lineNumber":768},{"declaringClass":"org.eclipse.jdt.internal.junit.runner.RemoteTestRunner","methodName":"run","fileName":"RemoteTestRunner.java","lineNumber":464},{"declaringClass":"org.eclipse.jdt.internal.junit.runner.RemoteTestRunner","methodName":"main","fileName":"RemoteTestRunner.java","lineNumber":210}]},"result":"ERROR","precondition":false,"level":2}]}]},{"number":12,"description":"Then Valido la cuenta creada","duration":7,"startTime":"2021-06-30T08:41:09.395-05:00[America/Bogota]","result":"SKIPPED","precondition":false,"level":0}],"userStory":{"id":"crear-cuenta-en-para-bank","storyName":"Crear cuenta en Para Bank","path":"file:///C:/Users/angel.vivas/Documents/Sophos/Semillero%20Automatización/MyProjects%20LOCAL/Gradle/SreenPlayBank/ScBank/lib/src/test/resources/features/login.feature","narrative":"yo como automatizador quiero crear una cuenta en Para Bank","type":"feature"},"featureTag":{"name":"Features/Crear cuenta en Para Bank","type":"feature","displayName":"Features/Crear cuenta en Para Bank"},"title":"Iniciar sesion en Para Bank","tags":[{"name":"Crear cuenta en Para Bank","type":"feature","displayName":"Crear cuenta en Para Bank"}],"startTime":"2021-06-30T08:40:26.845-05:00[America/Bogota]","duration":42583,"testFailureCause":{"errorType":"org.openqa.selenium.NoSuchElementException","message":"Cannot locate option with value: 12789\nFor documentation on this error, please visit: https://www.seleniumhq.org/exceptions/no_such_element.html\nBuild info: version: \u00273.141.59\u0027, revision: \u0027e82be7d358\u0027, time: \u00272018-11-14T08:17:03\u0027\nSystem info: host: \u0027SSMED5CG1081FB1\u0027, ip: \u0027192.168.0.18\u0027, os.name: \u0027Windows 10\u0027, os.arch: \u0027amd64\u0027, os.version: \u002710.0\u0027, java.version: \u00271.8.0_291\u0027\nDriver info: driver.version: unknown","stackTrace":[{"declaringClass":"com.sophos.semillero.tasks.CreateAccount","methodName":"performAs","fileName":"CreateAccount.java","lineNumber":20},{"declaringClass":"com.sophos.semillero.stepdefinitions.LoginStepDefinitions","methodName":"ingresoNombreDeUsuarioYPassword","fileName":"LoginStepDefinitions.java","lineNumber":41},{"declaringClass":"io.cucumber.java.Invoker","methodName":"invoke","fileName":"Invoker.java","lineNumber":27},{"declaringClass":"io.cucumber.java.JavaStepDefinition","methodName":"execute","fileName":"JavaStepDefinition.java","lineNumber":27},{"declaringClass":"io.cucumber.core.runner.PickleStepDefinitionMatch","methodName":"runStep","fileName":"PickleStepDefinitionMatch.java","lineNumber":63},{"declaringClass":"io.cucumber.core.runner.TestStep","methodName":"executeStep","fileName":"TestStep.java","lineNumber":64},{"declaringClass":"io.cucumber.core.runner.TestStep","methodName":"run","fileName":"TestStep.java","lineNumber":49},{"declaringClass":"io.cucumber.core.runner.PickleStepTestStep","methodName":"run","fileName":"PickleStepTestStep.java","lineNumber":46},{"declaringClass":"io.cucumber.core.runner.TestCase","methodName":"run","fileName":"TestCase.java","lineNumber":51},{"declaringClass":"io.cucumber.core.runner.Runner","methodName":"runPickle","fileName":"Runner.java","lineNumber":67},{"declaringClass":"io.cucumber.junit.FeatureRunner","methodName":"runChild","fileName":"FeatureRunner.java","lineNumber":83},{"declaringClass":"io.cucumber.junit.FeatureRunner","methodName":"runChild","fileName":"FeatureRunner.java","lineNumber":24},{"declaringClass":"io.cucumber.junit.CucumberSerenityRunner","methodName":"runChild","fileName":"CucumberSerenityRunner.java","lineNumber":227},{"declaringClass":"io.cucumber.junit.CucumberSerenityRunner","methodName":"runChild","fileName":"CucumberSerenityRunner.java","lineNumber":54},{"declaringClass":"org.eclipse.jdt.internal.junit4.runner.JUnit4TestReference","methodName":"run","fileName":"JUnit4TestReference.java","lineNumber":89},{"declaringClass":"org.eclipse.jdt.internal.junit.runner.TestExecution","methodName":"run","fileName":"TestExecution.java","lineNumber":40},{"declaringClass":"org.eclipse.jdt.internal.junit.runner.RemoteTestRunner","methodName":"runTests","fileName":"RemoteTestRunner.java","lineNumber":541},{"declaringClass":"org.eclipse.jdt.internal.junit.runner.RemoteTestRunner","methodName":"runTests","fileName":"RemoteTestRunner.java","lineNumber":768},{"declaringClass":"org.eclipse.jdt.internal.junit.runner.RemoteTestRunner","methodName":"run","fileName":"RemoteTestRunner.java","lineNumber":464},{"declaringClass":"org.eclipse.jdt.internal.junit.runner.RemoteTestRunner","methodName":"main","fileName":"RemoteTestRunner.java","lineNumber":210}]},"testFailureClassname":"org.openqa.selenium.NoSuchElementException","testFailureMessage":"Cannot locate option with value: 12789\nFor documentation on this error, please visit: https://www.seleniumhq.org/exceptions/no_such_element.html\nBuild info: version: \u00273.141.59\u0027, revision: \u0027e82be7d358\u0027, time: \u00272018-11-14T08:17:03\u0027\nSystem info: host: \u0027SSMED5CG1081FB1\u0027, ip: \u0027192.168.0.18\u0027, os.name: \u0027Windows 10\u0027, os.arch: \u0027amd64\u0027, os.version: \u002710.0\u0027, java.version: \u00271.8.0_291\u0027\nDriver info: driver.version: unknown","testFailureSummary":"ERROR;org.openqa.selenium.NoSuchElementException;Cannot locate option with value: 12789\nFor documentation on this error, please visit: https://www.seleniumhq.org/exceptions/no_such_element.html\nBuild info: version: \u00273.141.59\u0027, revision: \u0027e82be7d358\u0027, time: \u00272018-11-14T08:17:03\u0027\nSystem info: host: \u0027SSMED5CG1081FB1\u0027, ip: \u0027192.168.0.18\u0027, os.name: \u0027Windows 10\u0027, os.arch: \u0027amd64\u0027, os.version: \u002710.0\u0027, java.version: \u00271.8.0_291\u0027\nDriver info: driver.version: unknown;CreateAccount.java","projectKey":"","annotatedResult":"ERROR","sessionId":"184a4fa996c6c3d6d30c1a41f85b4034","driver":"chrome:angel vivas","isManualTestingUpToDate":false,"manual":false,"testSource":"Cucumber","actors":[{"name":"Angel Vivas","can":["browse the web"]}],"result":"ERROR"}