{"name":"Add Pet To Shopping Cart","id":"add-pet-to-shopping-cart;add-pet-to-shopping-cart","testSteps":[{"number":1,"description":"Given I want Login in \"https://petstore.octoperf.com/actions/Account.action?signonForm\u003d\"","duration":9986,"startTime":"2021-07-07T08:58:54.414831700-05:00[America/Bogota]","screenshots":[{"screenshot":"83f4ac1ce6f5c9c89d1899a52cfcb3da6f96cdfae765df12b7054d1778f0f0f9.png","timeStamp":1625666344401}],"result":"SUCCESS","precondition":false,"level":0,"children":[{"number":2,"description":"Jonathan opens the https://petstore.octoperf.com/actions/Account.action?signonForm\u003d","duration":9239,"startTime":"2021-07-07T08:58:55.141887700-05:00[America/Bogota]","screenshots":[{"screenshot":"83f4ac1ce6f5c9c89d1899a52cfcb3da6f96cdfae765df12b7054d1778f0f0f9.png","timeStamp":1625666344380}],"result":"SUCCESS","precondition":false,"level":1}]},{"number":3,"description":"When I assing \"pepito\" \"123\"","duration":4307,"startTime":"2021-07-07T08:59:04.403067900-05:00[America/Bogota]","screenshots":[{"screenshot":"6b46281ca95bebeb773453a8eabfb99a50ad22ad7dd8bbaea4ecc9cd24317260.png","timeStamp":1625666348710}],"result":"SUCCESS","precondition":false,"level":0,"children":[{"number":4,"description":"Jonathan store login","duration":4273,"startTime":"2021-07-07T08:59:04.430066600-05:00[America/Bogota]","screenshots":[{"screenshot":"e11ddb98efd64b709f076126736ba9968fba07d318a6da76f7abfdcbb7c232e9.png","timeStamp":1625666344804},{"screenshot":"6b46281ca95bebeb773453a8eabfb99a50ad22ad7dd8bbaea4ecc9cd24317260.png","timeStamp":1625666348703}],"result":"SUCCESS","precondition":false,"level":1,"children":[{"number":5,"description":"Jonathan enters \u0027pepito\u0027 into User name field","duration":1315,"startTime":"2021-07-07T08:59:04.850480700-05:00[America/Bogota]","screenshots":[{"screenshot":"80baec9aeef83da64d9edd6700af878ee0ab1e26d1ce3f0dac01444fecf0dd60.png","timeStamp":1625666346166}],"result":"SUCCESS","precondition":false,"level":2},{"number":6,"description":"Jonathan enters \u0027123\u0027 into Password field","duration":806,"startTime":"2021-07-07T08:59:06.170219100-05:00[America/Bogota]","screenshots":[{"screenshot":"80baec9aeef83da64d9edd6700af878ee0ab1e26d1ce3f0dac01444fecf0dd60.png","timeStamp":1625666346177},{"screenshot":"a330fb163e458d41a36f5969a549fc3286e0848a020d97e22b3538d4c9c8fa47.png","timeStamp":1625666346976}],"result":"SUCCESS","precondition":false,"level":2},{"number":7,"description":"Jonathan clicks on Login button","duration":1714,"startTime":"2021-07-07T08:59:06.980860-05:00[America/Bogota]","screenshots":[{"screenshot":"a330fb163e458d41a36f5969a549fc3286e0848a020d97e22b3538d4c9c8fa47.png","timeStamp":1625666346989},{"screenshot":"6b46281ca95bebeb773453a8eabfb99a50ad22ad7dd8bbaea4ecc9cd24317260.png","timeStamp":1625666348695}],"result":"SUCCESS","precondition":false,"level":2}]}]},{"number":8,"description":"Then I verify that the login is successful","duration":14,"startTime":"2021-07-07T08:59:08.712493200-05:00[America/Bogota]","screenshots":[{"screenshot":"6b46281ca95bebeb773453a8eabfb99a50ad22ad7dd8bbaea4ecc9cd24317260.png","timeStamp":1625666348727}],"result":"SUCCESS","precondition":false,"level":0},{"number":9,"description":"Given I want search pet type \"FISH\"","duration":1795,"startTime":"2021-07-07T08:59:08.730498500-05:00[America/Bogota]","screenshots":[{"screenshot":"963989d3ab8c1794bb2e40167253b3a0ff373863fb8c7311e75f801bacdfc82c.png","timeStamp":1625666350525}],"result":"SUCCESS","precondition":false,"level":0,"children":[{"number":10,"description":"Jonathan click to","duration":1757,"startTime":"2021-07-07T08:59:08.761497-05:00[America/Bogota]","screenshots":[{"screenshot":"963989d3ab8c1794bb2e40167253b3a0ff373863fb8c7311e75f801bacdfc82c.png","timeStamp":1625666350518}],"result":"SUCCESS","precondition":false,"level":1,"children":[{"number":11,"description":"Jonathan clicks on PET TYPE","duration":1219,"startTime":"2021-07-07T08:59:09.293534300-05:00[America/Bogota]","screenshots":[{"screenshot":"963989d3ab8c1794bb2e40167253b3a0ff373863fb8c7311e75f801bacdfc82c.png","timeStamp":1625666350513}],"result":"SUCCESS","precondition":false,"level":2}]}]},{"number":12,"description":"And Select pet breed \"Angelfish\"","duration":893,"startTime":"2021-07-07T08:59:10.527797500-05:00[America/Bogota]","screenshots":[{"screenshot":"4873816eadc9e7aab81ae1bfd968827bb6401294b0e512319291654fae9a5d54.png","timeStamp":1625666351421}],"result":"SUCCESS","precondition":false,"level":0,"children":[{"number":13,"description":"Jonathan click to","duration":877,"startTime":"2021-07-07T08:59:10.536797700-05:00[America/Bogota]","screenshots":[{"screenshot":"4873816eadc9e7aab81ae1bfd968827bb6401294b0e512319291654fae9a5d54.png","timeStamp":1625666351414}],"result":"SUCCESS","precondition":false,"level":1,"children":[{"number":14,"description":"Jonathan clicks on PET BREED","duration":863,"startTime":"2021-07-07T08:59:10.545799200-05:00[America/Bogota]","screenshots":[{"screenshot":"4873816eadc9e7aab81ae1bfd968827bb6401294b0e512319291654fae9a5d54.png","timeStamp":1625666351409}],"result":"SUCCESS","precondition":false,"level":2}]}]},{"number":15,"description":"When I decide the pet by the description \"Large\"","duration":1490,"startTime":"2021-07-07T08:59:11.423422800-05:00[America/Bogota]","screenshots":[{"screenshot":"4896b0f29ce685a2cc4d2e7cb50c6896c9b97eedee231a649514ffbd407ec3b0.png","timeStamp":1625666352913}],"result":"SUCCESS","precondition":false,"level":0,"children":[{"number":16,"description":"Jonathan save info","duration":398,"startTime":"2021-07-07T08:59:11.450426900-05:00[America/Bogota]","screenshots":[{"screenshot":"4873816eadc9e7aab81ae1bfd968827bb6401294b0e512319291654fae9a5d54.png","timeStamp":1625666351848}],"result":"SUCCESS","precondition":false,"level":1},{"number":17,"description":"Jonathan click to","duration":1054,"startTime":"2021-07-07T08:59:11.850477600-05:00[America/Bogota]","screenshots":[{"screenshot":"4896b0f29ce685a2cc4d2e7cb50c6896c9b97eedee231a649514ffbd407ec3b0.png","timeStamp":1625666352904}],"result":"SUCCESS","precondition":false,"level":1,"children":[{"number":18,"description":"Jonathan clicks on PET VIEW","duration":1035,"startTime":"2021-07-07T08:59:11.864472100-05:00[America/Bogota]","screenshots":[{"screenshot":"4896b0f29ce685a2cc4d2e7cb50c6896c9b97eedee231a649514ffbd407ec3b0.png","timeStamp":1625666352899}],"result":"SUCCESS","precondition":false,"level":2}]}]},{"number":19,"description":"Then I verify that show view item information","duration":10,"startTime":"2021-07-07T08:59:12.916975100-05:00[America/Bogota]","screenshots":[{"screenshot":"4896b0f29ce685a2cc4d2e7cb50c6896c9b97eedee231a649514ffbd407ec3b0.png","timeStamp":1625666352926}],"result":"SUCCESS","precondition":false,"level":0}],"userStory":{"id":"add-pet-to-shopping-cart","storyName":"Add Pet To Shopping Cart","path":"file:///C:/Users/elber.ceballos/Documents/trabajos%20en%20grupo/SemilleroScreenPlayPractica/ProyectoTiendaMascotas/lib/src/test/resources/com/sophossolutions/features/StoreViewItemInfo.feature","narrative":"  As a tester i want to add pet to shopping cart","type":"feature"},"featureTag":{"name":"Features/Add Pet To Shopping Cart","type":"feature","displayName":"Features/Add Pet To Shopping Cart"},"title":"Add Pet To Shopping Cart","backgroundTitle":"","backgroundDescription":"","startTime":"2021-07-07T08:58:54.046293-05:00[America/Bogota]","duration":18885,"projectKey":"","sessionId":"13e01c9627ac81580e8f21e49963b726","driver":"chrome:jonathan","isManualTestingUpToDate":false,"manual":false,"testSource":"Cucumber","actors":[{"name":"Jonathan","can":["browse the web"]}],"result":"SUCCESS"}